googleimagedownloader/googleimagedownloader.py
googleimagedownloader-3.1.0.dist-info/LICENSE
googleimagedownloader-3.1.0.dist-info/METADATA
googleimagedownloader-3.1.0.dist-info/WHEEL
googleimagedownloader-3.1.0.dist-info/top_level.txt
googleimagedownloader-3.1.0.dist-info/RECORD
