Metadata-Version: 2.1
Name: googleimagedownloader
Version: 3.1.0
Summary: 
Home-page: https://github.com/soumilshah1995/GoogleImageDownloader
Author: Soumil Nitin Shah
Author-email: soushah@my.bridgeport.edu
License: MIT
Platform: UNKNOWN
Classifier: License :: OSI Approved :: MIT License
Classifier: Programming Language :: Python :: 3
Classifier: Programming Language :: Python :: 3.7
Requires-Dist: requests-futures
Requires-Dist: pandas
Requires-Dist: bs4
Requires-Dist: requests
